README.md
setup.py
apistar_autoapp/__init__.py
apistar_autoapp/autoapp.py
apistar_autoapp/printer.py
apistar_autoapp.egg-info/PKG-INFO
apistar_autoapp.egg-info/SOURCES.txt
apistar_autoapp.egg-info/dependency_links.txt
apistar_autoapp.egg-info/requires.txt
apistar_autoapp.egg-info/top_level.txt