Metadata-Version: 2.1
Name: apistar-autoapp
Version: 0.6.1
Summary: Automatically import APIStar sub apps
Home-page: https://github.com/jeffbuttars/apistar-autoapp
Author: Jeff Buttars
Author-email: jeff@jeffbuttars.com
License: Apache License 2.0
Platform: UNKNOWN
Classifier: Environment :: Web Environment
Classifier: Intended Audience :: Developers
Classifier: License :: OSI Approved :: Apache Software License
Classifier: Operating System :: OS Independent
Classifier: Topic :: Internet :: WWW/HTTP
Classifier: Programming Language :: Python :: 3
Classifier: Programming Language :: Python :: 3 :: Only
Classifier: Programming Language :: Python :: 3.5
Classifier: Programming Language :: Python :: 3.6
